dalia/__init__.py
dalia/csvv.py
dalia/hierarchy.py
dalia/tests/__init__.py
dalia/tests/test_csvv.py
dalia/tests/test_hierarchy.py
dalia-0.2.2.dist-info/AUTHORS.rst
dalia-0.2.2.dist-info/LICENSE
dalia-0.2.2.dist-info/METADATA
dalia-0.2.2.dist-info/WHEEL
dalia-0.2.2.dist-info/top_level.txt
dalia-0.2.2.dist-info/RECORD
