Metadata-Version: 2.1
Name: dalia
Version: 0.2.2
Summary: Goddess of fate, giver and taker of goods
Home-page: https://github.com/brews/dalia
Author: Brewster Malevich
Author-email: bmalevich@rhg.com
License: UNKNOWN
Keywords: dalia
Platform: UNKNOWN
Classifier: Development Status :: 2 - Pre-Alpha
Classifier: Intended Audience :: Developers
Classifier: Intended Audience :: Science/Research
Classifier: License :: OSI Approved :: Apache Software License
Classifier: Natural Language :: English
Classifier: Programming Language :: Python :: 3 :: Only
Classifier: Programming Language :: Python :: 3
Classifier: Programming Language :: Python :: 3.7
Classifier: Topic :: Scientific/Engineering
Classifier: Topic :: Sociology
Requires-Python: >=3.7
Requires-Dist: numpy
Requires-Dist: pyyaml
Requires-Dist: anytree
Provides-Extra: dev
Requires-Dist: pytest ; extra == 'dev'
Requires-Dist: pytest-cov ; extra == 'dev'
Requires-Dist: wheel ; extra == 'dev'
Requires-Dist: flake8 ; extra == 'dev'
Requires-Dist: black ; extra == 'dev'
Requires-Dist: twine ; extra == 'dev'
Provides-Extra: doc
Requires-Dist: sphinx ; extra == 'doc'
Requires-Dist: sphinx-rtd-theme ; extra == 'doc'
Requires-Dist: numpydoc ; extra == 'doc'
Requires-Dist: ipython ; extra == 'doc'
Provides-Extra: test
Requires-Dist: pytest ; extra == 'test'
